pve_api/__init__.py
pve_api/api.py
pve_api/exception/AuthorizationException.py
pve_api/exception/RequestException.py
pve_api/exception/__init__.py
pve_api/model/AptPackage.py
pve_api/model/Certificate.py
pve_api/model/Directory.py
pve_api/model/LocalDisk.py
pve_api/model/LvmThin.py
pve_api/model/MyList.py
pve_api/model/Network.py
pve_api/model/PveNode.py
pve_api/model/QemuCPU.py
pve_api/model/QemuMachine.py
pve_api/model/Version.py
pve_api/model/ZfsPool.py
pve_api/model/__init__.py
pve_api/model/qemu/QemuItem.py
pve_api/model/qemu/QemuStatus.py
pve_api/model/qemu/__init__.py
pve_api/util/SizeConvert.py
pve_api/util/__init__.py
pve_api-1.1.3.dist-info/METADATA
pve_api-1.1.3.dist-info/WHEEL
pve_api-1.1.3.dist-info/top_level.txt
pve_api-1.1.3.dist-info/RECORD
