Metadata-Version: 2.4
Name: pve_api
Version: 1.1.3
Summary: Python library for Proxmox VE API
Author-email: schlibra <schlibra@163.com>
Project-URL: Homepage, https://github.com/schlibra/pve_api
Project-URL: Source, https://github.com/schlibra/pve_api
Project-URL: Issues, https://github.com/schlibra/pve_api/issues
Requires-Python: >=3.9
Requires-Dist: requests>=2.32.4
